{
  "eny_0007_mimicw": {
    "templateId": "eny_0007_mimicw"
  },
  "eny_0018_lbtough": {
    "templateId": "eny_0018_lbtough"
  },
  "eny_0021_agmelee": {
    "templateId": "eny_0021_agmelee"
  },
  "eny_0023_aghornb": {
    "templateId": "eny_0023_aghornb"
  },
  "eny_0025_agrange": {
    "templateId": "eny_0025_agrange"
  },
  "eny_0027_agscorp": {
    "templateId": "eny_0027_agscorp"
  },
  "eny_0029_lbmob": {
    "templateId": "eny_0029_lbmob"
  },
  "eny_0033_lbhunt": {
    "templateId": "eny_0033_lbhunt"
  },
  "eny_0039_agcanno": {
    "templateId": "eny_0039_agcanno"
  },
  "eny_0045_agtrinit": {
    "templateId": "eny_0045_agtrinit"
  },
  "eny_0046_lbshamman": {
    "templateId": "eny_0046_lbshamman"
  },
  "eny_0047_firebat": {
    "templateId": "eny_0047_firebat"
  },
  "eny_0048_hvybow": {
    "templateId": "eny_0048_hvybow"
  },
  "eny_0049_rogue": {
    "templateId": "eny_0049_rogue"
  },
  "eny_0050_hound": {
    "templateId": "eny_0050_hound"
  },
  "eny_0051_rodin": {
    "templateId": "eny_0051_rodin"
  },
  "eny_0052_palesent": {
    "templateId": "eny_0052_palesent"
  },
  "eny_0053_hsmob": {
    "templateId": "eny_0053_hsmob"
  },
  "eny_0054_hsmino": {
    "templateId": "eny_0054_hsmino"
  },
  "eny_0055_hscrane": {
    "templateId": "eny_0055_hscrane"
  },
  "eny_0057_dog": {
    "templateId": "eny_0057_dog"
  },
  "eny_0058_agdisk": {
    "templateId": "eny_0058_agdisk"
  },
  "eny_0059_erhound": {
    "templateId": "eny_0059_erhound"
  },
  "eny_0060_lbmad": {
    "templateId": "eny_0060_lbmad"
  },
  "eny_0061_palecore": {
    "templateId": "eny_0061_palecore"
  },
  "eny_0062_paletent": {
    "templateId": "eny_0062_paletent"
  },
  "eny_0063_agmelee2": {
    "templateId": "eny_0063_agmelee2"
  },
  "eny_0064_agrange2": {
    "templateId": "eny_0064_agrange2"
  },
  "eny_0065_lbmob2": {
    "templateId": "eny_0065_lbmob2"
  },
  "eny_0066_lbhunt2": {
    "templateId": "eny_0066_lbhunt2"
  },
  "eny_0067_hound2": {
    "templateId": "eny_0067_hound2"
  },
  "eny_0068_lbtough2": {
    "templateId": "eny_0068_lbtough2"
  },
  "eny_0069_aghornb2": {
    "templateId": "eny_0069_aghornb2"
  },
  "eny_0070_agscorp2": {
    "templateId": "eny_0070_agscorp2"
  }
}